EPMS/__init__.py
EPMS/deserialization.py
EPMS/serialization.py
EPMS-0.0.8.dist-info/LICENSE
EPMS-0.0.8.dist-info/METADATA
EPMS-0.0.8.dist-info/WHEEL
EPMS-0.0.8.dist-info/top_level.txt
EPMS-0.0.8.dist-info/RECORD
