Metadata-Version: 2.1
Name: EPMS
Version: 0.0.8
Summary: The Expressive Polyphonic MIDI Serializer is a tool to turn MIDI files into a model-friendly, expressive representation for ML projects.
Home-page: https://github.com/petcomputacaoufrgs/EPMS
Author: PET Computação UFRGS
Author-email: pet@inf.ufrgs.br
License: UNKNOWN
Project-URL: LSTM model using EPMS, https://github.com/petcomputacaoufrgs/papagaio
Platform: UNKNOWN
Classifier: Programming Language :: Python :: 3
Classifier: License :: OSI Approved :: MIT License
Classifier: Operating System :: OS Independent
Requires-Python: >=3.6
License-File: LICENSE
